detection_models/__init__.py
detection_models/bbox_detector.py
detection_models/detection_models.py
detection_models/object_detector.py
detection_models/results.py
detection_models/utils.py
detection_models-0.1.2.dist-info/AUTHORS.rst
detection_models-0.1.2.dist-info/LICENSE
detection_models-0.1.2.dist-info/METADATA
detection_models-0.1.2.dist-info/WHEEL
detection_models-0.1.2.dist-info/top_level.txt
detection_models-0.1.2.dist-info/RECORD
