Metadata-Version: 2.1
Name: detection-models
Version: 0.1.2
Summary: Data structures for running TensorFlow Object Detection API models
Home-page: https://github.com/autognc/detection_models
Author: Gavin C. Martin
Author-email: gavinmartin@utexas.edu
License: MIT license
Keywords: detection_models
Platform: UNKNOWN
Classifier: Development Status :: 2 - Pre-Alpha
Classifier: Intended Audience :: Developers
Classifier: License :: OSI Approved :: MIT License
Classifier: Natural Language :: English
Classifier: Programming Language :: Python :: 3.5
Classifier: Programming Language :: Python :: 3.6
Requires-Dist: Cython
Requires-Dist: contextlib2
Requires-Dist: pillow
Requires-Dist: lxml
Requires-Dist: jupyter
Requires-Dist: matplotlib
Requires-Dist: tensorflow
